Vendy_RPC_modules/__init__.py
Vendy_RPC_modules/src/__init__.py
Vendy_RPC_modules/src/main.py
vendy_rpc-1.0.0.dist-info/licenses/LICENSE
vendy_rpc-1.0.0.dist-info/METADATA
vendy_rpc-1.0.0.dist-info/WHEEL
vendy_rpc-1.0.0.dist-info/top_level.txt
vendy_rpc-1.0.0.dist-info/RECORD
