Metadata-Version: 2.4
Name: vendy-rpc
Version: 1.0.0
Summary: RPC 모듈 - @ZEV 가 만든 파이썬 유일한 디스코드 rpc
Author: Vendy
License: MIT
Keywords: discord,rpc,rich-presence,websocket,discord-rpc
Classifier: Development Status :: 4 - Beta
Classifier: Intended Audience :: Developers
Classifier: License :: OSI Approved :: MIT License
Classifier: Programming Language :: Python :: 3
Classifier: Programming Language :: Python :: 3.7
Classifier: Programming Language :: Python :: 3.8
Classifier: Programming Language :: Python :: 3.9
Classifier: Programming Language :: Python :: 3.10
Classifier: Programming Language :: Python :: 3.11
Classifier: Programming Language :: Python :: 3.12
Classifier: Topic :: Communications :: Chat
Classifier: Topic :: Software Development :: Libraries :: Python Modules
Requires-Python: >=3.7
License-File: LICENSE
Requires-Dist: websocket-client>=1.6.0
Dynamic: license-file
Dynamic: requires-python
